COPYING
MANIFEST.in
README.rst
bootstrap-buildout.py
buildout.cfg
requirements.txt
setup.cfg
setup.py
version.txt
bob/__init__.py
bob.paper.biosig2016.egg-info/PKG-INFO
bob.paper.biosig2016.egg-info/SOURCES.txt
bob.paper.biosig2016.egg-info/dependency_links.txt
bob.paper.biosig2016.egg-info/entry_points.txt
bob.paper.biosig2016.egg-info/not-zip-safe
bob.paper.biosig2016.egg-info/requires.txt
bob.paper.biosig2016.egg-info/top_level.txt
bob/paper/__init__.py
bob/paper/biosig2016/__init__.py
bob/paper/biosig2016/algorithm/__init__.py
bob/paper/biosig2016/algorithm/lda.py
bob/paper/biosig2016/algorithm/mlp.py
bob/paper/biosig2016/config/__init__.py
bob/paper/biosig2016/config/algorithm/__init__.py
bob/paper/biosig2016/config/algorithm/mlp_sigmoid_200_neurons_stoch.py
bob/paper/biosig2016/config/database/__init__.py
bob/paper/biosig2016/config/database/asvspoof_cm.py
bob/paper/biosig2016/config/database/avspoof_detect_physical.py
bob/paper/biosig2016/config/extractor/__init__.py
bob/paper/biosig2016/config/extractor/mean_spectrum_32ms.py
bob/paper/biosig2016/config/extractor/mean_std_spectrum_256ms_shift_10ms.py
bob/paper/biosig2016/config/extractor/mean_std_spectrum_32ms.py
bob/paper/biosig2016/config/extractor/std_spectrum_32ms.py
bob/paper/biosig2016/config/grid/__init__.py
bob/paper/biosig2016/config/grid/normal.py
bob/paper/biosig2016/config/preprocessor/__init__.py
bob/paper/biosig2016/config/preprocessor/energy_2gauss_remove_head_tail.py
bob/paper/biosig2016/config/preprocessor/no_preprocessing.py
bob/paper/biosig2016/extractor/SpectralStatistics.py
bob/paper/biosig2016/extractor/__init__.py
bob/paper/biosig2016/preprocessor/Energy_2Gauss_Remove_Head_Tail.py
bob/paper/biosig2016/preprocessor/No_Preprocessing.py
bob/paper/biosig2016/preprocessor/__init__.py
bob/paper/biosig2016/script/__init__.py
bob/paper/biosig2016/script/compute_EER_perattack_eval.py
bob/paper/biosig2016/script/evaluate_pad.py
bob/paper/biosig2016/script/spoof_mlp.py
bob/paper/biosig2016/tools/FileSelector.py
bob/paper/biosig2016/tools/__init__.py
bob/paper/biosig2016/tools/algorithm.py
bob/paper/biosig2016/utils/__init__.py
bob/paper/biosig2016/utils/norm.py
doc/conf.py
doc/index.rst