Metadata-Version: 1.1
Name: bob.paper.biosig2016
Version: 1.0.1
Summary: Presentation Attack Detection Using Long Term Spectral Statistics for Trustworthy Speaker Verification
Home-page: UNKNOWN
Author: Hannah Muckenhirn
Author-email: hannah.muckenhirn@idiap.ch
License: GPLv3
Keywords: Speaker verification,Spoofing,Long Term Spectral Statistics
Platform: UNKNOWN
Classifier: Development Status :: 3 - Alpha
Classifier: Intended Audience :: Developers
Classifier: License :: OSI Approved :: GNU General Public License v3 (GPLv3)
Classifier: Natural Language :: English
Classifier: Programming Language :: Python
Classifier: Topic :: Scientific/Engineering :: Artificial Intelligence
